createdryverail/__init__.py
createdryverail/dryveCode.py
create_drive_rail-1.0.dist-info/METADATA
create_drive_rail-1.0.dist-info/WHEEL
create_drive_rail-1.0.dist-info/top_level.txt
create_drive_rail-1.0.dist-info/RECORD
