Metadata-Version: 2.1
Name: create-drive-rail
Version: 1.0
Summary: Dryve D1 script created by 2 undergraduate robotic students of Aalborg University
Home-page: https://github.com/Nicher1/Dryve-repository-for-dummies.git
Author: Nichlas Overgaard Laugesen, Elias Thomassen Dam
License: MIT
Project-URL: Documentation, https://github.com/Nicher1/Dryve-repository-for-dummies
Project-URL: Source, https://github.com/Nicher1/Dryve-repository-for-dummies
Project-URL: Tracker, https://github.com/Nicher1/Dryve-repository-for-dummies/issues
Keywords: robotics DryveD1 Python Script Rail Create
Classifier: Development Status :: 5 - Production/Stable
Classifier: Intended Audience :: Developers
Classifier: Topic :: Software Development :: Libraries
Classifier: License :: OSI Approved :: MIT License
Classifier: Programming Language :: Python :: 3.9
Classifier: Programming Language :: Python :: 3.10
Classifier: Programming Language :: Python :: 3.11
Requires-Python: >=3.6
Requires-Dist: sockets
